gadgetfinder/__init__.py
gadgetfinder/gadget.py
gadgetfinder/gadget_finder.py
gadgetfinder/shell.py
gadgetfinder/trie.py
gadgetfinder/utils.py
gadgetfinder-1.0.0.dist-info/LICENSE
gadgetfinder-1.0.0.dist-info/METADATA
gadgetfinder-1.0.0.dist-info/WHEEL
gadgetfinder-1.0.0.dist-info/top_level.txt
gadgetfinder-1.0.0.dist-info/RECORD
