Metadata-Version: 2.1
Name: gadgetfinder
Version: 1.0.0
Summary: A tool with interactive shell for finding gadgets in executable files
Home-page: https://https://github.com/jmc0/GadgetFinder
Author: 733g10
Author-email: rla141@sfu.ca, zma30@sfu.ca, zca110@sfu.ca
License: UNKNOWN
Project-URL: Bug Tracker, https://https://github.com/jmc0/GadgetFinder/issues
Platform: UNKNOWN
Classifier: Programming Language :: Python :: 3
Classifier: License :: OSI Approved :: MIT License
Classifier: Operating System :: OS Independent
Requires-Python: >=3.6
License-File: LICENSE
Requires-Dist: capstone
Requires-Dist: keystone
Requires-Dist: pyelftools
Requires-Dist: pefile
